[
  {
    "Name": "test",
    "FileSource": "C:\\Users\\valen\\OneDrive\\Bureau\\testMove\\Or",
    "FileTarget": "C:\\Users\\valen\\OneDrive\\Bureau\\testMove\\Target",
    "FileSize": "0",
    "FileTransferTim": "946",
    "Time": "29/02/2024 16:3:30",
    "CryptoTime": "139"
  },
  {
    "Name": "test",
    "FileSource": "C:\\Users\\valen\\OneDrive\\Bureau\\testMove\\Or",
    "FileTarget": "C:\\Users\\valen\\OneDrive\\Bureau\\testMove\\Target",
    "FileSize": "0",
    "FileTransferTim": "348",
    "Time": "29/02/2024 16:3:47",
    "CryptoTime": "36"
  },
  {
    "Name": "test",
    "FileSource": "C:\\Users\\valen\\OneDrive\\Bureau\\testMove\\Or",
    "FileTarget": "C:\\Users\\valen\\OneDrive\\Bureau\\testMove\\Target",
    "FileSize": "0",
    "FileTransferTim": "323",
    "Time": "29/02/2024 16:3:53",
    "CryptoTime": "13"
  },
  {
    "Name": "test",
    "FileSource": "C:\\Users\\valen\\OneDrive\\Bureau\\testMove\\Or",
    "FileTarget": "C:\\Users\\valen\\OneDrive\\Bureau\\testMove\\Target",
    "FileSize": "0",
    "FileTransferTim": "376",
    "Time": "29/02/2024 16:3:56",
    "CryptoTime": "19"
  },
  {
    "Name": "test",
    "FileSource": "C:\\Users\\valen\\OneDrive\\Bureau\\testMove\\Or",
    "FileTarget": "C:\\Users\\valen\\OneDrive\\Bureau\\testMove\\Target",
    "FileSize": "0",
    "FileTransferTim": "192",
    "Time": "29/02/2024 16:6:08",
    "CryptoTime": "143"
  },
  {
    "Name": "test",
    "FileSource": "C:\\Users\\valen\\OneDrive\\Bureau\\testMove\\Or",
    "FileTarget": "C:\\Users\\valen\\OneDrive\\Bureau\\testMove\\Target",
    "FileSize": "0",
    "FileTransferTim": "157",
    "Time": "29/02/2024 16:19:45",
    "CryptoTime": "115"
  },
  {
    "Name": "test",
    "FileSource": "C:\\Users\\valen\\OneDrive\\Bureau\\testMove\\Or",
    "FileTarget": "C:\\Users\\valen\\OneDrive\\Bureau\\testMove\\Target",
    "FileSize": "0",
    "FileTransferTim": "200",
    "Time": "29/02/2024 16:20:51",
    "CryptoTime": "125"
  },
  {
    "Name": "test",
    "FileSource": "C:\\Users\\valen\\OneDrive\\Bureau\\testMove\\Or",
    "FileTarget": "C:\\Users\\valen\\OneDrive\\Bureau\\testMove\\Target",
    "FileSize": "0",
    "FileTransferTim": "168",
    "Time": "29/02/2024 16:22:21",
    "CryptoTime": "116"
  },
  {
    "Name": "Test2",
    "FileSource": "C:\\Users\\valen\\OneDrive\\Bureau\\EasySaveConsol_2",
    "FileTarget": "C:\\Users\\valen\\OneDrive\\Bureau\\testMove\\Target",
    "FileSize": "1",
    "FileTransferTim": "70",
    "Time": "29/02/2024 16:25:14",
    "CryptoTime": "0"
  },
  {
    "Name": "Test2",
    "FileSource": "C:\\Users\\valen\\OneDrive\\Bureau\\EasySaveConsol_2",
    "FileTarget": "C:\\Users\\valen\\OneDrive\\Bureau\\testMove\\Target",
    "FileSize": "1",
    "FileTransferTim": "93",
    "Time": "29/02/2024 16:26:20",
    "CryptoTime": "0"
  },
  {
    "Name": "Test2",
    "FileSource": "C:\\Users\\valen\\OneDrive\\Bureau\\EasySaveConsol_2",
    "FileTarget": "C:\\Users\\valen\\OneDrive\\Bureau\\testMove\\Target",
    "FileSize": "1",
    "FileTransferTim": "16",
    "Time": "29/02/2024 16:26:28",
    "CryptoTime": "0"
  }
]